odoo/addons/account_invoice_supplierinfo_update_discount/README.rst
odoo/addons/account_invoice_supplierinfo_update_discount/__init__.py
odoo/addons/account_invoice_supplierinfo_update_discount/__manifest__.py
odoo/addons/account_invoice_supplierinfo_update_discount/i18n/account_invoice_supplierinfo_update_discount.pot
odoo/addons/account_invoice_supplierinfo_update_discount/i18n/ar.po
odoo/addons/account_invoice_supplierinfo_update_discount/i18n/bs.po
odoo/addons/account_invoice_supplierinfo_update_discount/i18n/ca.po
odoo/addons/account_invoice_supplierinfo_update_discount/i18n/cs.po
odoo/addons/account_invoice_supplierinfo_update_discount/i18n/de.po
odoo/addons/account_invoice_supplierinfo_update_discount/i18n/en_GB.po
odoo/addons/account_invoice_supplierinfo_update_discount/i18n/es.po
odoo/addons/account_invoice_supplierinfo_update_discount/i18n/es_CR.po
odoo/addons/account_invoice_supplierinfo_update_discount/i18n/es_EC.po
odoo/addons/account_invoice_supplierinfo_update_discount/i18n/es_MX.po
odoo/addons/account_invoice_supplierinfo_update_discount/i18n/et.po
odoo/addons/account_invoice_supplierinfo_update_discount/i18n/fr.po
odoo/addons/account_invoice_supplierinfo_update_discount/i18n/fr_CH.po
odoo/addons/account_invoice_supplierinfo_update_discount/i18n/hr.po
odoo/addons/account_invoice_supplierinfo_update_discount/i18n/hu.po
odoo/addons/account_invoice_supplierinfo_update_discount/i18n/it.po
odoo/addons/account_invoice_supplierinfo_update_discount/i18n/ja.po
odoo/addons/account_invoice_supplierinfo_update_discount/i18n/lt.po
odoo/addons/account_invoice_supplierinfo_update_discount/i18n/mk.po
odoo/addons/account_invoice_supplierinfo_update_discount/i18n/mn.po
odoo/addons/account_invoice_supplierinfo_update_discount/i18n/nb.po
odoo/addons/account_invoice_supplierinfo_update_discount/i18n/nl.po
odoo/addons/account_invoice_supplierinfo_update_discount/i18n/nl_BE.po
odoo/addons/account_invoice_supplierinfo_update_discount/i18n/nl_NL.po
odoo14_addon_account_invoice_supplierinfo_update_discount-14.0.1.0.1.dev6.dist-info/METADATA
odoo14_addon_account_invoice_supplierinfo_update_discount-14.0.1.0.1.dev6.dist-info/WHEEL
odoo14_addon_account_invoice_supplierinfo_update_discount-14.0.1.0.1.dev6.dist-info/top_level.txt
odoo14_addon_account_invoice_supplierinfo_update_discount-14.0.1.0.1.dev6.dist-info/RECORD
