Metadata-Version: 2.1
Name: odoo14-addon-account_invoice_supplierinfo_update_discount
Version: 14.0.1.0.1.dev6
Summary: In the supplier invoice, automatically update all products whose discount on the line is different from the supplier discount
Home-page: https://github.com/OCA/account-invoicing
Author: GRAP, Odoo Community Association (OCA)
Author-email: support@odoo-community.org
License: AGPL-3
Classifier: Programming Language :: Python
Classifier: Framework :: Odoo
Classifier: Framework :: Odoo :: 14.0
Classifier: License :: OSI Approved :: GNU Affero General Public License v3
Requires-Python: >=3.6
Requires-Dist: odoo14-addon-account-invoice-supplierinfo-update
Requires-Dist: odoo14-addon-purchase-discount
Requires-Dist: odoo<14.1dev,>=14.0a
